ilps28qsw.py
circuitpython_ilps28qsw-0.2.0.dist-info/licenses/LICENSE
circuitpython_ilps28qsw-0.2.0.dist-info/METADATA
circuitpython_ilps28qsw-0.2.0.dist-info/WHEEL
circuitpython_ilps28qsw-0.2.0.dist-info/top_level.txt
circuitpython_ilps28qsw-0.2.0.dist-info/RECORD
