Metadata-Version: 2.4
Name: circuitpython-ilps28qsw
Version: 0.2.0
Summary: CircuitPython module for the ILPS28QSW absolute digital output barometer.
Author: mrv96
License: MIT
Project-URL: Homepage, https://github.com/mrv96/CircuitPython_ILPS28QSW
Keywords: adafruit,blinka,circuitpython,micropython,ilps28qsw,st,stmicroelectronics,pressure,temperature,sensor,absolute
Classifier: Intended Audience :: Developers
Classifier: Topic :: Software Development :: Libraries
Classifier: Topic :: Software Development :: Embedded Systems
Classifier: Topic :: System :: Hardware
Classifier: License :: OSI Approved :: MIT License
Classifier: Programming Language :: Python :: 3
Requires-Python: >=3.9
License-File: LICENSE
Requires-Dist: Adafruit-Blinka
Requires-Dist: adafruit-circuitpython-busdevice
Provides-Extra: optional
Dynamic: license-file
